{
  "type": "GROUP",
"name": "Global Information",
"path": "",
"pathFormatted": "group_missing-name-b06d1",
"stats": {
    "name": "Global Information",
    "numberOfRequests": {
        "total": 6,
        "ok": 6,
        "ko": 0
    },
    "minResponseTime": {
        "total": 214,
        "ok": 214,
        "ko": 0
    },
    "maxResponseTime": {
        "total": 954,
        "ok": 954,
        "ko": 0
    },
    "meanResponseTime": {
        "total": 582,
        "ok": 582,
        "ko": 0
    },
    "standardDeviation": {
        "total": 362,
        "ok": 362,
        "ko": 0
    },
    "percentiles1": {
        "total": 579,
        "ok": 579,
        "ko": 0
    },
    "percentiles2": {
        "total": 942,
        "ok": 942,
        "ko": 0
    },
    "percentiles3": {
        "total": 952,
        "ok": 952,
        "ko": 0
    },
    "percentiles4": {
        "total": 954,
        "ok": 954,
        "ko": 0
    },
    "group1": {
    "name": "t < 800 ms",
    "count": 3,
    "percentage": 50
},
    "group2": {
    "name": "800 ms < t < 1200 ms",
    "count": 3,
    "percentage": 50
},
    "group3": {
    "name": "t > 1200 ms",
    "count": 0,
    "percentage": 0
},
    "group4": {
    "name": "failed",
    "count": 0,
    "percentage": 0
},
    "meanNumberOfRequestsPerSecond": {
        "total": 2.0,
        "ok": 2.0,
        "ko": 0
    }
},
"contents": {
"req_goto---page--31218": {
        "type": "REQUEST",
        "name": "Goto #{page}",
"path": "Goto #{page}",
"pathFormatted": "req_goto---page--31218",
"stats": {
    "name": "Goto #{page}",
    "numberOfRequests": {
        "total": 3,
        "ok": 3,
        "ko": 0
    },
    "minResponseTime": {
        "total": 932,
        "ok": 932,
        "ko": 0
    },
    "maxResponseTime": {
        "total": 954,
        "ok": 954,
        "ko": 0
    },
    "meanResponseTime": {
        "total": 944,
        "ok": 944,
        "ko": 0
    },
    "standardDeviation": {
        "total": 9,
        "ok": 9,
        "ko": 0
    },
    "percentiles1": {
        "total": 945,
        "ok": 945,
        "ko": 0
    },
    "percentiles2": {
        "total": 950,
        "ok": 950,
        "ko": 0
    },
    "percentiles3": {
        "total": 953,
        "ok": 953,
        "ko": 0
    },
    "percentiles4": {
        "total": 954,
        "ok": 954,
        "ko": 0
    },
    "group1": {
    "name": "t < 800 ms",
    "count": 0,
    "percentage": 0
},
    "group2": {
    "name": "800 ms < t < 1200 ms",
    "count": 3,
    "percentage": 100
},
    "group3": {
    "name": "t > 1200 ms",
    "count": 0,
    "percentage": 0
},
    "group4": {
    "name": "failed",
    "count": 0,
    "percentage": 0
},
    "meanNumberOfRequestsPerSecond": {
        "total": 1.0,
        "ok": 1.0,
        "ko": 0
    }
}
    },"req_goto---page--re-0f9bf": {
        "type": "REQUEST",
        "name": "Goto #{page} Redirect 1",
"path": "Goto #{page} Redirect 1",
"pathFormatted": "req_goto---page--re-0f9bf",
"stats": {
    "name": "Goto #{page} Redirect 1",
    "numberOfRequests": {
        "total": 3,
        "ok": 3,
        "ko": 0
    },
    "minResponseTime": {
        "total": 214,
        "ok": 214,
        "ko": 0
    },
    "maxResponseTime": {
        "total": 226,
        "ok": 226,
        "ko": 0
    },
    "meanResponseTime": {
        "total": 220,
        "ok": 220,
        "ko": 0
    },
    "standardDeviation": {
        "total": 5,
        "ok": 5,
        "ko": 0
    },
    "percentiles1": {
        "total": 219,
        "ok": 219,
        "ko": 0
    },
    "percentiles2": {
        "total": 223,
        "ok": 223,
        "ko": 0
    },
    "percentiles3": {
        "total": 225,
        "ok": 225,
        "ko": 0
    },
    "percentiles4": {
        "total": 226,
        "ok": 226,
        "ko": 0
    },
    "group1": {
    "name": "t < 800 ms",
    "count": 3,
    "percentage": 100
},
    "group2": {
    "name": "800 ms < t < 1200 ms",
    "count": 0,
    "percentage": 0
},
    "group3": {
    "name": "t > 1200 ms",
    "count": 0,
    "percentage": 0
},
    "group4": {
    "name": "failed",
    "count": 0,
    "percentage": 0
},
    "meanNumberOfRequestsPerSecond": {
        "total": 1.0,
        "ok": 1.0,
        "ko": 0
    }
}
    }
}

}